[{"name":"Sinatra + Rack + Rake + ActiveRecord","regex":"Sinatra + Rack + Rake + ActiveRecord","url":"/blog/sinatra-app/","desc":"How to build an application with Sinatra, Rack and ActiveRecord?","type":"article","tags":"sinatra ruby rest api","uuid":"5ced2003-a396-4324-bfec-a719ed6b6ca2"},{"name":"Creating a dynamic toolbar button for Komodo X","regex":"Creating a dynamic toolbar button for Komodo X","url":"/blog/dynamic-buttons-in-komodo/","desc":"I'm finding side toolbar very useful for me. More over, you can write...","type":"article","tags":"komodo userscripts javascript","uuid":"106255bb-f880-4898-8c39-0a6712961752"},{"name":"Add global menu for Komodo X in Unity","regex":"Add global menu for Komodo X in Unity","url":"/blog/globalmenu-4-life/","desc":"Missing global menu for Komodo X in Ubuntu Unity? This article will...","type":"article","tags":"globalmenu komodo","uuid":"214222f2-9ae8-48dd-9799-bda788d91a1f"},{"name":"Komodo Color Picker by babobski","regex":"Komodo Color Picker by babobski","url":"/blog/komodo-color-picker/","desc":"Nice color picker that supports RGBA colors","type":"article","tags":"komodo colorpicker add-on","uuid":"fe3b77cd-7f9d-43ea-8f6f-8e481a030f00"},{"name":"My Top 5 monospaced fonts","regex":"My Top 5 monospaced fonts","url":"/blog/my-top-5-monospaced-fonts/","desc":"My top 5 monospaced fonts for Linux","type":"article","tags":"fonts top-5 monospace","uuid":"93f4b145-4a09-46d2-98d0-65dab9b3c418"},{"name":"Install dnscrypt and configure it in elementary OS 0.4","regex":"Install dnscrypt and configure it in elementary OS 0.4","url":"/blog/dnscrypt-and-elementary-os/","desc":"A guide about how to install dnscrypt and configure it.","type":"article","tags":"dnscrypt elementary os","uuid":"9c31ef82-8b51-450a-81de-b3b7a3e5bc1b"},{"name":"How to make git diff looks better","regex":"How to make git diff looks better","url":"/blog/how-to-make-git-diff-looks-better/","desc":"Wondering How to make git diff looks a bit better? This article can...","type":"article","tags":"git","uuid":"7a2cb21c-1ce8-4d05-bbb9-d35dd55b6654"},{"name":"Better search!","regex":"Better search!","url":"/blog/better-search-yay/","desc":"Today I'm introducing an update to the search engine on my web-site....","type":"article","tags":"defman.me search javascript","uuid":"ebb5756b-1c10-48cb-91dc-752cf6d1b422"},{"name":"Komodo X - My Opinion","regex":"Komodo X - My Opinion","url":"/blog/komodo-x-my-opinion/","desc":"My opinion about Komodo X","type":"article","tags":"komodo-x opinion 10","uuid":"7924c5d9-30c0-4cd7-8df2-b709165fc7f2"},{"name":"Git 2.9: What's new?","regex":"Git 2.9: What's new?","url":"/blog/git-2-9-whats-new/","desc":"Git 2.9 has been released. There are some cool features that I want...","type":"article","tags":"git","uuid":"52ea742e-a8d3-4d0c-a245-0cc4de3632f7"},{"name":"Hello HTTPS","regex":"Hello HTTPS","url":"/blog/hello-https/","desc":"Finally defman.me is now available at https://defman.me (no http...","type":"article","tags":"https security letsencrypt","uuid":"33a9f4e7-9db2-45f7-9dfb-1c974f186d92"},{"name":"Livereload and Hanami","regex":"Livereload and Hanami","url":"/blog/hanami-love-livereload/","desc":"A guide how to make LiveReload work in Hanami","type":"article","tags":"hanami livereload ruby","uuid":"c012f0f2-7be2-48d7-9257-a70ef0b86714"},{"name":"Better screenshots in elementary OS","regex":"Better screenshots in elementary OS","url":"/blog/elementary-os-screenshots/","desc":"There are 2 different tools to make screenshots in eOS. We'll merge...","type":"article","tags":"elementary bash script shell screenshots","uuid":"191e6d6d-ea1f-4e34-8b0a-89c7586be810"},{"name":"Scheme to Interface project","regex":"Scheme to Interface project","url":"/projects/ko-s2i/","desc":"This tool allows you to convert Komodo 9 color scheme to Komodo 10.","tags":"komodo schemes interface ui","type":"project","lang":"ruby","uuid":"38750675-0c2a-4819-9b6d-f2850cfd14f6"},{"name":"Xemmet","regex":"Xemmet","url":"/projects/xemmet/","desc":"Xemmet - Emmet for Komodo X","tags":"komodo emmet html css fast coding","type":"project","lang":"javascript","uuid":"a86cfd2e-eea2-4251-91cb-48c11cf6745b"},{"name":"Komodo Terminal Butterfly","regex":"Komodo Terminal Butterfly","url":"/projects/komodo-terminal/","desc":"Docks the Butterfly terminal in Komodo","tags":"komodo terminal butterfly add-on","type":"project","lang":"javascript","uuid":"c132706a-4afe-4658-a6ee-a4daa1a1eb0a"},{"name":"Unikitty","regex":"Unikitty","url":"/schemes/unikitty/","desc":"Unikitty color scheme","type":"scheme","uuid":"2db11fd3-8620-458d-a56f-14de6cb70fe5"},{"name":"Forest","regex":"Forest","url":"/schemes/forest/","desc":"Base16 Atelier Forest light color scheme for Komodo.","type":"scheme","uuid":"85711aa3-1524-4521-a245-44f992edb1d8"},{"name":"Flat","regex":"Flat","url":"/schemes/flat/","desc":"Flat color scheme","type":"scheme","uuid":"0ae23ba0-19ab-43e9-8441-97031d7e164f"},{"name":"Railscasts","regex":"Railscasts","url":"/schemes/railscasts/","desc":"Railscasts color scheme for Komodo X","type":"scheme","uuid":"1bdb9098-3b66-4cbb-8008-f1e560874855"},{"name":"Materia","regex":"Materia","url":"/schemes/materia/","desc":"Material-based color scheme","type":"scheme","uuid":"daf9ee9b-6f80-43ea-9084-c46624102092"},{"name":"Github","regex":"Github","url":"/schemes/github/","desc":"Github color scheme","type":"scheme","uuid":"811d0713-bda7-418f-8ca0-5009fbcac465"},{"name":"Oceanicnext","regex":"Oceanicnext","url":"/schemes/oceanicnext/","desc":"Oceanicnext color scheme for Komodo X","type":"scheme","uuid":"4cfca088-7569-4224-b042-a04ace9614ac"}]